pytest_fmu_filter/__init__.py
pytest_fmu_filter/md.py
pytest_fmu_filter/plugin.py
pytest_fmu_filter-0.1.3.dist-info/licenses/LICENSE
pytest_fmu_filter-0.1.3.dist-info/METADATA
pytest_fmu_filter-0.1.3.dist-info/WHEEL
pytest_fmu_filter-0.1.3.dist-info/entry_points.txt
pytest_fmu_filter-0.1.3.dist-info/top_level.txt
pytest_fmu_filter-0.1.3.dist-info/RECORD
