Metadata-Version: 2.4
Name: pytest-fmu-filter
Version: 0.1.3
Summary: A pytest plugin to filter fmus
Author-email: coder <coder@timeintegral.ai>
Maintainer-email: coder <coder@timeintegral.ai>
License: 
Project-URL: Repository, https://github.com/time-integral/pytest-fmu-filter
Classifier: Framework :: Pytest
Classifier: Development Status :: 4 - Beta
Classifier: Intended Audience :: Developers
Classifier: Topic :: Software Development :: Testing
Classifier: Operating System :: OS Independent
Classifier: Programming Language :: Python
Classifier: Programming Language :: Python :: 3.10
Classifier: Programming Language :: Python :: 3.11
Classifier: Programming Language :: Python :: 3.12
Classifier: Programming Language :: Python :: 3.13
Classifier: Programming Language :: Python :: 3 :: Only
Classifier: Programming Language :: Python :: Implementation :: CPython
Classifier: Programming Language :: Python :: Implementation :: PyPy
Classifier: License :: OSI Approved :: MIT License
Requires-Python: >=3.10
License-File: LICENSE
Requires-Dist: pytest>=7.0.0
Dynamic: license-file
